[
{
  "pk": 3, 
  "model": "desktop.document2", 
  "fields": {
    "search": null, 
    "uuid": "41b726d0-e4df-ad33-8c61-14ba87116318", 
    "extra": "", 
    "type": "oozie-workflow2", 
    "description": "Oozie job to run java programs", 
    "is_history": false, 
    "parent_directory": [
      "a68783c1-6d6f-4eda-bf66-df4b54bb7563", 
      1, 
      false
    ], 
    "is_managed": false, 
    "last_modified": "2019-06-06T06:24:27", 
    "version": 1, 
    "owner": [
      "cloudera"
    ], 
    "dependencies": [
      [
        "63a6a0ac-5a10-40b5-b46a-a05b04e26bf1", 
        1, 
        true
      ], 
      [
        "505e90bc-4869-4ecf-ad9f-f5fcd329b76e", 
        1, 
        true
      ]
    ], 
    "data": "{\"layout\": [{\"oozieRows\": [{\"enableOozieDropOnBefore\": true, \"enableOozieDropOnSide\": true, \"enableOozieDrop\": false, \"widgets\": [{\"status\": \"\", \"logsURL\": \"\", \"name\": \"Java program\", \"widgetType\": \"java-widget\", \"oozieMovable\": true, \"ooziePropertiesExpanded\": false, \"externalIdUrl\": \"\", \"properties\": {}, \"externalId\": \"\", \"isLoading\": true, \"offset\": 0, \"actionURL\": \"\", \"progress\": 0, \"klass\": \"card card-widget span12\", \"oozieExpanded\": false, \"id\": \"d8b26f9b-27dc-381e-0fcb-b2a0d1bd4792\", \"size\": 12}], \"id\": \"4528baa6-516d-8eb4-276a-49509f50c0f8\", \"columns\": []}], \"rows\": [{\"enableOozieDropOnBefore\": true, \"enableOozieDropOnSide\": true, \"enableOozieDrop\": false, \"widgets\": [{\"status\": \"\", \"logsURL\": \"\", \"name\": \"Start\", \"widgetType\": \"start-widget\", \"oozieMovable\": false, \"ooziePropertiesExpanded\": false, \"externalIdUrl\": \"\", \"properties\": {}, \"externalId\": \"\", \"isLoading\": true, \"offset\": 0, \"actionURL\": \"\", \"progress\": 0, \"klass\": \"card card-widget span12\", \"oozieExpanded\": false, \"id\": \"3f107997-04cc-8733-60a9-a4bb62cebffc\", \"size\": 12}], \"id\": \"2901b9d4-aa2f-4f6b-4f23-ba17d60027e4\", \"columns\": []}, {\"enableOozieDropOnBefore\": true, \"enableOozieDropOnSide\": true, \"enableOozieDrop\": false, \"widgets\": [{\"status\": \"\", \"logsURL\": \"\", \"name\": \"Java program\", \"widgetType\": \"java-widget\", \"oozieMovable\": true, \"ooziePropertiesExpanded\": false, \"externalIdUrl\": \"\", \"properties\": {}, \"externalId\": \"\", \"isLoading\": true, \"offset\": 0, \"actionURL\": \"\", \"progress\": 0, \"klass\": \"card card-widget span12\", \"oozieExpanded\": false, \"id\": \"d8b26f9b-27dc-381e-0fcb-b2a0d1bd4792\", \"size\": 12}], \"id\": \"4528baa6-516d-8eb4-276a-49509f50c0f8\", \"columns\": []}, {\"enableOozieDropOnBefore\": true, \"enableOozieDropOnSide\": true, \"enableOozieDrop\": false, \"widgets\": [{\"status\": \"\", \"logsURL\": \"\", \"name\": \"End\", \"widgetType\": \"end-widget\", \"oozieMovable\": false, \"ooziePropertiesExpanded\": false, \"externalIdUrl\": \"\", \"properties\": {}, \"externalId\": \"\", \"isLoading\": true, \"offset\": 0, \"actionURL\": \"\", \"progress\": 0, \"klass\": \"card card-widget span12\", \"oozieExpanded\": false, \"id\": \"33430f0f-ebfa-c3ec-f237-3e77efa03d0a\", \"size\": 12}], \"id\": \"f91ea45a-cec9-4c85-1dae-73a232d81c4f\", \"columns\": []}, {\"enableOozieDropOnBefore\": true, \"enableOozieDropOnSide\": true, \"enableOozieDrop\": false, \"widgets\": [{\"status\": \"\", \"logsURL\": \"\", \"name\": \"Kill\", \"widgetType\": \"kill-widget\", \"oozieMovable\": true, \"ooziePropertiesExpanded\": false, \"externalIdUrl\": \"\", \"properties\": {}, \"externalId\": \"\", \"isLoading\": true, \"offset\": 0, \"actionURL\": \"\", \"progress\": 0, \"klass\": \"card card-widget span12\", \"oozieExpanded\": false, \"id\": \"17c9c895-5a16-7443-bb81-f34b30b21548\", \"size\": 12}], \"id\": \"358bdc43-20d0-4a9f-36e4-1926b2fa4c8f\", \"columns\": []}], \"oozieEndRow\": {\"enableOozieDropOnBefore\": true, \"enableOozieDropOnSide\": true, \"enableOozieDrop\": false, \"widgets\": [{\"status\": \"\", \"logsURL\": \"\", \"name\": \"End\", \"widgetType\": \"end-widget\", \"oozieMovable\": false, \"ooziePropertiesExpanded\": false, \"externalIdUrl\": \"\", \"properties\": {}, \"externalId\": \"\", \"isLoading\": true, \"offset\": 0, \"actionURL\": \"\", \"progress\": 0, \"klass\": \"card card-widget span12\", \"oozieExpanded\": false, \"id\": \"33430f0f-ebfa-c3ec-f237-3e77efa03d0a\", \"size\": 12}], \"id\": \"f91ea45a-cec9-4c85-1dae-73a232d81c4f\", \"columns\": []}, \"oozieKillRow\": {\"enableOozieDropOnBefore\": true, \"enableOozieDropOnSide\": true, \"enableOozieDrop\": false, \"widgets\": [{\"status\": \"\", \"logsURL\": \"\", \"name\": \"Kill\", \"widgetType\": \"kill-widget\", \"oozieMovable\": true, \"ooziePropertiesExpanded\": false, \"externalIdUrl\": \"\", \"properties\": {}, \"externalId\": \"\", \"isLoading\": true, \"offset\": 0, \"actionURL\": \"\", \"progress\": 0, \"klass\": \"card card-widget span12\", \"oozieExpanded\": false, \"id\": \"17c9c895-5a16-7443-bb81-f34b30b21548\", \"size\": 12}], \"id\": \"358bdc43-20d0-4a9f-36e4-1926b2fa4c8f\", \"columns\": []}, \"enableOozieDropOnAfter\": true, \"oozieStartRow\": {\"enableOozieDropOnBefore\": true, \"enableOozieDropOnSide\": true, \"enableOozieDrop\": false, \"widgets\": [{\"status\": \"\", \"logsURL\": \"\", \"name\": \"Start\", \"widgetType\": \"start-widget\", \"oozieMovable\": false, \"ooziePropertiesExpanded\": false, \"externalIdUrl\": \"\", \"properties\": {}, \"externalId\": \"\", \"isLoading\": true, \"offset\": 0, \"actionURL\": \"\", \"progress\": 0, \"klass\": \"card card-widget span12\", \"oozieExpanded\": false, \"id\": \"3f107997-04cc-8733-60a9-a4bb62cebffc\", \"size\": 12}], \"id\": \"2901b9d4-aa2f-4f6b-4f23-ba17d60027e4\", \"columns\": []}, \"klass\": \"card card-home card-column span12\", \"enableOozieDropOnBefore\": true, \"drops\": [\"temp\"], \"id\": \"e1fe516d-8da7-4b19-7695-6d6713918eb4\", \"size\": 12}], \"workflow\": {\"properties\": {\"job_xml\": \"\", \"description\": \"Oozie job to run java programs\", \"parameters\": [{\"name\": \"oozie.use.system.libpath\", \"value\": true}], \"sla_enabled\": false, \"deployment_dir\": \"/user/hue/oozie/workspaces/hue-oozie-1559578450.36\", \"schema_version\": \"uri:oozie:workflow:0.5\", \"properties\": [], \"show_arrows\": true, \"wf1_id\": null, \"sla\": [{\"key\": \"enabled\", \"value\": false}, {\"key\": \"nominal-time\", \"value\": \"${nominal_time}\"}, {\"key\": \"should-start\", \"value\": \"\"}, {\"key\": \"should-end\", \"value\": \"${30 * MINUTES}\"}, {\"key\": \"max-duration\", \"value\": \"\"}, {\"key\": \"alert-events\", \"value\": \"\"}, {\"key\": \"alert-contact\", \"value\": \"\"}, {\"key\": \"notification-msg\", \"value\": \"\"}, {\"key\": \"upstream-apps\", \"value\": \"\"}]}, \"name\": \"My Workflow\", \"hasKillNode\": true, \"versions\": [\"uri:oozie:workflow:0.4\", \"uri:oozie:workflow:0.4.5\", \"uri:oozie:workflow:0.5\"], \"isDirty\": false, \"movedNode\": null, \"linkMapping\": {\"17c9c895-5a16-7443-bb81-f34b30b21548\": [], \"33430f0f-ebfa-c3ec-f237-3e77efa03d0a\": [], \"d8b26f9b-27dc-381e-0fcb-b2a0d1bd4792\": [\"33430f0f-ebfa-c3ec-f237-3e77efa03d0a\"], \"3f107997-04cc-8733-60a9-a4bb62cebffc\": [\"d8b26f9b-27dc-381e-0fcb-b2a0d1bd4792\"]}, \"nodeIds\": [\"3f107997-04cc-8733-60a9-a4bb62cebffc\", \"33430f0f-ebfa-c3ec-f237-3e77efa03d0a\", \"17c9c895-5a16-7443-bb81-f34b30b21548\", \"d8b26f9b-27dc-381e-0fcb-b2a0d1bd4792\"], \"nodes\": [{\"name\": \"Start\", \"associatedDocumentLoading\": true, \"children\": [{\"to\": \"d8b26f9b-27dc-381e-0fcb-b2a0d1bd4792\"}], \"actionParametersFetched\": false, \"properties\": {}, \"associatedDocumentUuid\": null, \"type\": \"start-widget\", \"id\": \"3f107997-04cc-8733-60a9-a4bb62cebffc\", \"actionParameters\": []}, {\"name\": \"End\", \"associatedDocumentLoading\": true, \"children\": [], \"actionParametersFetched\": false, \"properties\": {\"body\": \"\", \"cc\": \"\", \"to\": \"\", \"enableMail\": false, \"attachment\": \"\", \"content_type\": \"text/plain\", \"subject\": \"\"}, \"associatedDocumentUuid\": null, \"type\": \"end-widget\", \"id\": \"33430f0f-ebfa-c3ec-f237-3e77efa03d0a\", \"actionParameters\": []}, {\"name\": \"Kill\", \"associatedDocumentLoading\": true, \"children\": [], \"actionParametersFetched\": false, \"properties\": {\"body\": \"\", \"cc\": \"\", \"to\": \"\", \"enableMail\": false, \"message\": \"Action failed, error message[${wf:errorMessage(wf:lastErrorNode())}]\", \"subject\": \"\"}, \"associatedDocumentUuid\": null, \"type\": \"kill-widget\", \"id\": \"17c9c895-5a16-7443-bb81-f34b30b21548\", \"actionParameters\": []}, {\"name\": \"java-d8b2\", \"associatedDocumentLoading\": true, \"children\": [{\"to\": \"33430f0f-ebfa-c3ec-f237-3e77efa03d0a\"}, {\"error\": \"17c9c895-5a16-7443-bb81-f34b30b21548\"}], \"actionParametersFetched\": false, \"properties\": {\"files\": [], \"job_xml\": [], \"jar_path\": \"/user/jenkins/examples/apps/java-main/lib/oozie-examples-4.1.0-cdh5.13.0.test.jar\", \"java_opts\": [], \"retry_max\": [], \"retry_interval\": [], \"job_properties\": [], \"capture_output\": false, \"prepares\": [], \"arguments\": [], \"main_class\": \"org.apache.oozie.example.DemoJavaMain\", \"credentials\": [], \"sla\": [{\"key\": \"enabled\", \"value\": false}, {\"key\": \"nominal-time\", \"value\": \"${nominal_time}\"}, {\"key\": \"should-start\", \"value\": \"\"}, {\"key\": \"should-end\", \"value\": \"${30 * MINUTES}\"}, {\"key\": \"max-duration\", \"value\": \"\"}, {\"key\": \"alert-events\", \"value\": \"\"}, {\"key\": \"alert-contact\", \"value\": \"\"}, {\"key\": \"notification-msg\", \"value\": \"\"}, {\"key\": \"upstream-apps\", \"value\": \"\"}], \"archives\": []}, \"associatedDocumentUuid\": null, \"type\": \"java-widget\", \"id\": \"d8b26f9b-27dc-381e-0fcb-b2a0d1bd4792\", \"actionParameters\": []}], \"id\": 3, \"nodeNamesMapping\": {\"17c9c895-5a16-7443-bb81-f34b30b21548\": \"Kill\", \"33430f0f-ebfa-c3ec-f237-3e77efa03d0a\": \"End\", \"d8b26f9b-27dc-381e-0fcb-b2a0d1bd4792\": \"java-d8b2\", \"3f107997-04cc-8733-60a9-a4bb62cebffc\": \"Start\"}, \"uuid\": \"41b726d0-e4df-ad33-8c61-14ba87116318\"}}", 
    "is_trashed": false, 
    "name": "My Workflow"
  }
}
]
