[
{
  "pk": 27, 
  "model": "desktop.document2", 
  "fields": {
    "search": null, 
    "uuid": "ae6ff55f-b6df-d8cc-715a-9484748eacea", 
    "extra": "", 
    "type": "oozie-workflow2", 
    "description": "", 
    "is_history": false, 
    "parent_directory": [
      "a68783c1-6d6f-4eda-bf66-df4b54bb7563", 
      1, 
      false
    ], 
    "is_managed": false, 
    "last_modified": "2019-06-09T22:59:25", 
    "version": 1, 
    "owner": [
      "cloudera"
    ], 
    "dependencies": [], 
    "data": "{\"layout\": [{\"oozieRows\": [{\"enableOozieDropOnBefore\": true, \"enableOozieDropOnSide\": true, \"enableOozieDrop\": false, \"widgets\": [{\"status\": \"\", \"logsURL\": \"\", \"name\": \"todays date\", \"widgetType\": \"shell-widget\", \"oozieMovable\": true, \"ooziePropertiesExpanded\": false, \"gridsterHeight\": 0, \"externalIdUrl\": \"\", \"properties\": {}, \"externalId\": \"\", \"isLoading\": false, \"offset\": 0, \"actionURL\": \"\", \"progress\": 0, \"klass\": \"card card-widget span12\", \"oozieExpanded\": false, \"id\": \"3a44236a-5e93-b4b0-18cd-6a19d317e069\", \"size\": 12}], \"id\": \"66638709-a1cf-1c81-0d1d-84dfd3f3c7de\", \"columns\": []}], \"rows\": [{\"enableOozieDropOnBefore\": true, \"enableOozieDropOnSide\": true, \"enableOozieDrop\": false, \"widgets\": [{\"status\": \"\", \"logsURL\": \"\", \"name\": \"Start\", \"widgetType\": \"start-widget\", \"oozieMovable\": false, \"ooziePropertiesExpanded\": false, \"gridsterHeight\": 0, \"externalIdUrl\": \"\", \"properties\": {}, \"externalId\": \"\", \"isLoading\": false, \"offset\": 0, \"actionURL\": \"\", \"progress\": 0, \"klass\": \"card card-widget span12\", \"oozieExpanded\": false, \"id\": \"3f107997-04cc-8733-60a9-a4bb62cebffc\", \"size\": 12}], \"id\": \"7009349a-ee7a-e788-9808-e1308fa9667b\", \"columns\": []}, {\"enableOozieDropOnBefore\": true, \"enableOozieDropOnSide\": true, \"enableOozieDrop\": false, \"widgets\": [{\"status\": \"\", \"logsURL\": \"\", \"name\": \"todays date\", \"widgetType\": \"shell-widget\", \"oozieMovable\": true, \"ooziePropertiesExpanded\": false, \"gridsterHeight\": 0, \"externalIdUrl\": \"\", \"properties\": {}, \"externalId\": \"\", \"isLoading\": false, \"offset\": 0, \"actionURL\": \"\", \"progress\": 0, \"klass\": \"card card-widget span12\", \"oozieExpanded\": false, \"id\": \"3a44236a-5e93-b4b0-18cd-6a19d317e069\", \"size\": 12}], \"id\": \"66638709-a1cf-1c81-0d1d-84dfd3f3c7de\", \"columns\": []}, {\"enableOozieDropOnBefore\": true, \"enableOozieDropOnSide\": true, \"enableOozieDrop\": false, \"widgets\": [{\"status\": \"\", \"logsURL\": \"\", \"name\": \"End\", \"widgetType\": \"end-widget\", \"oozieMovable\": false, \"ooziePropertiesExpanded\": false, \"gridsterHeight\": 0, \"externalIdUrl\": \"\", \"properties\": {}, \"externalId\": \"\", \"isLoading\": false, \"offset\": 0, \"actionURL\": \"\", \"progress\": 0, \"klass\": \"card card-widget span12\", \"oozieExpanded\": false, \"id\": \"33430f0f-ebfa-c3ec-f237-3e77efa03d0a\", \"size\": 12}], \"id\": \"fb08c4dc-d1cf-181b-fc23-fbdda6a22896\", \"columns\": []}, {\"enableOozieDropOnBefore\": true, \"enableOozieDropOnSide\": true, \"enableOozieDrop\": false, \"widgets\": [{\"status\": \"\", \"logsURL\": \"\", \"name\": \"Kill\", \"widgetType\": \"kill-widget\", \"oozieMovable\": true, \"ooziePropertiesExpanded\": false, \"gridsterHeight\": 0, \"externalIdUrl\": \"\", \"properties\": {}, \"externalId\": \"\", \"isLoading\": false, \"offset\": 0, \"actionURL\": \"\", \"progress\": 0, \"klass\": \"card card-widget span12\", \"oozieExpanded\": false, \"id\": \"17c9c895-5a16-7443-bb81-f34b30b21548\", \"size\": 12}], \"id\": \"36d2a036-a20b-43db-163a-2e539482748d\", \"columns\": []}], \"oozieEndRow\": {\"enableOozieDropOnBefore\": true, \"enableOozieDropOnSide\": true, \"enableOozieDrop\": false, \"widgets\": [{\"status\": \"\", \"logsURL\": \"\", \"name\": \"End\", \"widgetType\": \"end-widget\", \"oozieMovable\": false, \"ooziePropertiesExpanded\": false, \"gridsterHeight\": 0, \"externalIdUrl\": \"\", \"properties\": {}, \"externalId\": \"\", \"isLoading\": false, \"offset\": 0, \"actionURL\": \"\", \"progress\": 0, \"klass\": \"card card-widget span12\", \"oozieExpanded\": false, \"id\": \"33430f0f-ebfa-c3ec-f237-3e77efa03d0a\", \"size\": 12}], \"id\": \"fb08c4dc-d1cf-181b-fc23-fbdda6a22896\", \"columns\": []}, \"oozieKillRow\": {\"enableOozieDropOnBefore\": true, \"enableOozieDropOnSide\": true, \"enableOozieDrop\": false, \"widgets\": [{\"status\": \"\", \"logsURL\": \"\", \"name\": \"Kill\", \"widgetType\": \"kill-widget\", \"oozieMovable\": true, \"ooziePropertiesExpanded\": false, \"gridsterHeight\": 0, \"externalIdUrl\": \"\", \"properties\": {}, \"externalId\": \"\", \"isLoading\": false, \"offset\": 0, \"actionURL\": \"\", \"progress\": 0, \"klass\": \"card card-widget span12\", \"oozieExpanded\": false, \"id\": \"17c9c895-5a16-7443-bb81-f34b30b21548\", \"size\": 12}], \"id\": \"36d2a036-a20b-43db-163a-2e539482748d\", \"columns\": []}, \"enableOozieDropOnAfter\": true, \"oozieStartRow\": {\"enableOozieDropOnBefore\": true, \"enableOozieDropOnSide\": true, \"enableOozieDrop\": false, \"widgets\": [{\"status\": \"\", \"logsURL\": \"\", \"name\": \"Start\", \"widgetType\": \"start-widget\", \"oozieMovable\": false, \"ooziePropertiesExpanded\": false, \"gridsterHeight\": 0, \"externalIdUrl\": \"\", \"properties\": {}, \"externalId\": \"\", \"isLoading\": false, \"offset\": 0, \"actionURL\": \"\", \"progress\": 0, \"klass\": \"card card-widget span12\", \"oozieExpanded\": false, \"id\": \"3f107997-04cc-8733-60a9-a4bb62cebffc\", \"size\": 12}], \"id\": \"7009349a-ee7a-e788-9808-e1308fa9667b\", \"columns\": []}, \"klass\": \"card card-home card-column span12\", \"enableOozieDropOnBefore\": true, \"drops\": [\"temp\"], \"id\": \"41923120-5f9c-1041-393d-b43197f976f7\", \"size\": 12}], \"workflow\": {\"properties\": {\"job_xml\": \"\", \"description\": \"\", \"parameters\": [{\"name\": \"oozie.use.system.libpath\", \"value\": true}], \"sla_enabled\": false, \"deployment_dir\": \"/user/hue/oozie/workspaces/hue-oozie-1560146327.28\", \"schema_version\": \"uri:oozie:workflow:0.5\", \"sla\": [{\"value\": false, \"key\": \"enabled\"}, {\"value\": \"${nominal_time}\", \"key\": \"nominal-time\"}, {\"value\": \"\", \"key\": \"should-start\"}, {\"value\": \"${30 * MINUTES}\", \"key\": \"should-end\"}, {\"value\": \"\", \"key\": \"max-duration\"}, {\"value\": \"\", \"key\": \"alert-events\"}, {\"value\": \"\", \"key\": \"alert-contact\"}, {\"value\": \"\", \"key\": \"notification-msg\"}, {\"value\": \"\", \"key\": \"upstream-apps\"}], \"show_arrows\": true, \"wf1_id\": null, \"properties\": []}, \"name\": \"shellaction\", \"hasKillNode\": true, \"versions\": [\"uri:oozie:workflow:0.4\", \"uri:oozie:workflow:0.4.5\", \"uri:oozie:workflow:0.5\"], \"isDirty\": true, \"movedNode\": null, \"linkMapping\": {\"33430f0f-ebfa-c3ec-f237-3e77efa03d0a\": [], \"3a44236a-5e93-b4b0-18cd-6a19d317e069\": [\"33430f0f-ebfa-c3ec-f237-3e77efa03d0a\"], \"3f107997-04cc-8733-60a9-a4bb62cebffc\": [\"3a44236a-5e93-b4b0-18cd-6a19d317e069\"], \"17c9c895-5a16-7443-bb81-f34b30b21548\": []}, \"nodeIds\": [\"3f107997-04cc-8733-60a9-a4bb62cebffc\", \"33430f0f-ebfa-c3ec-f237-3e77efa03d0a\", \"17c9c895-5a16-7443-bb81-f34b30b21548\", \"3a44236a-5e93-b4b0-18cd-6a19d317e069\"], \"nodes\": [{\"name\": \"Start\", \"associatedDocumentLoading\": true, \"children\": [{\"to\": \"3a44236a-5e93-b4b0-18cd-6a19d317e069\"}], \"actionParametersFetched\": false, \"properties\": {}, \"associatedDocumentUuid\": null, \"type\": \"start-widget\", \"id\": \"3f107997-04cc-8733-60a9-a4bb62cebffc\", \"actionParameters\": []}, {\"name\": \"End\", \"associatedDocumentLoading\": true, \"children\": [], \"actionParametersFetched\": false, \"properties\": {\"body\": \"\", \"cc\": \"\", \"to\": \"\", \"enableMail\": false, \"attachment\": \"\", \"content_type\": \"text/plain\", \"subject\": \"\"}, \"associatedDocumentUuid\": null, \"type\": \"end-widget\", \"id\": \"33430f0f-ebfa-c3ec-f237-3e77efa03d0a\", \"actionParameters\": []}, {\"name\": \"Kill\", \"associatedDocumentLoading\": true, \"children\": [], \"actionParametersFetched\": false, \"properties\": {\"body\": \"\", \"cc\": \"\", \"to\": \"\", \"enableMail\": false, \"message\": \"Action failed, error message[${wf:errorMessage(wf:lastErrorNode())}]\", \"subject\": \"\"}, \"associatedDocumentUuid\": null, \"type\": \"kill-widget\", \"id\": \"17c9c895-5a16-7443-bb81-f34b30b21548\", \"actionParameters\": []}, {\"name\": \"shell-3a44\", \"associatedDocumentLoading\": true, \"children\": [{\"to\": \"33430f0f-ebfa-c3ec-f237-3e77efa03d0a\"}, {\"error\": \"17c9c895-5a16-7443-bb81-f34b30b21548\"}], \"actionParametersFetched\": false, \"properties\": {\"files\": [], \"job_xml\": \"\", \"retry_interval\": [], \"retry_max\": [], \"job_properties\": [], \"capture_output\": true, \"shell_command\": \"date\", \"arguments\": [], \"prepares\": [], \"credentials\": [], \"env_var\": [], \"sla\": [{\"value\": false, \"key\": \"enabled\"}, {\"value\": \"${nominal_time}\", \"key\": \"nominal-time\"}, {\"value\": \"\", \"key\": \"should-start\"}, {\"value\": \"${30 * MINUTES}\", \"key\": \"should-end\"}, {\"value\": \"\", \"key\": \"max-duration\"}, {\"value\": \"\", \"key\": \"alert-events\"}, {\"value\": \"\", \"key\": \"alert-contact\"}, {\"value\": \"\", \"key\": \"notification-msg\"}, {\"value\": \"\", \"key\": \"upstream-apps\"}], \"archives\": []}, \"associatedDocumentUuid\": null, \"type\": \"shell-widget\", \"id\": \"3a44236a-5e93-b4b0-18cd-6a19d317e069\", \"actionParameters\": []}], \"id\": null, \"nodeNamesMapping\": {\"33430f0f-ebfa-c3ec-f237-3e77efa03d0a\": \"End\", \"3a44236a-5e93-b4b0-18cd-6a19d317e069\": \"shell-3a44\", \"3f107997-04cc-8733-60a9-a4bb62cebffc\": \"Start\", \"17c9c895-5a16-7443-bb81-f34b30b21548\": \"Kill\"}, \"uuid\": \"ae6ff55f-b6df-d8cc-715a-9484748eacea\"}}", 
    "is_trashed": false, 
    "name": "shellaction"
  }
}
]
